utils/__init__.py
utils/rgb2gray.py
zjutcv/__init__.py
zjutcv/version.py
zjutcv/image/__init__.py
zjutcv/image/colorspace.py
zjutcv-0.0.0.dist-info/LICENSE
zjutcv-0.0.0.dist-info/METADATA
zjutcv-0.0.0.dist-info/WHEEL
zjutcv-0.0.0.dist-info/top_level.txt
zjutcv-0.0.0.dist-info/RECORD
