Metadata-Version: 2.1
Name: zjutcv
Version: 0.0.0
Summary: ZJUT toolbox for computer vision
Home-page: https://github.com/zjutcv/zjutcv
Author: ZJUTCV contributors
Author-email: ykn@zjut.edu.cn
License: UNKNOWN
Keywords: computer vision
Platform: UNKNOWN
Classifier: Development Status :: 4 - Beta
Classifier: License :: OSI Approved :: Apache Software License
Classifier: Operating System :: OS Independent
Classifier: Programming Language :: Python :: 3
Classifier: Programming Language :: Python :: 3.6
Classifier: Programming Language :: Python :: 3.7
Classifier: Programming Language :: Python :: 3.8
Classifier: Programming Language :: Python :: 3.9
Classifier: Programming Language :: Python :: 3.10
Classifier: Topic :: Utilities
Requires-Dist: mmcv
Requires-Dist: addict
Requires-Dist: numpy
Requires-Dist: packaging
Requires-Dist: Pillow
Requires-Dist: pyyaml
Requires-Dist: yapf
Requires-Dist: regex ; sys_platform == "win32"
Provides-Extra: all
Requires-Dist: pytest-runner ; extra == 'all'
Requires-Dist: ninja ; extra == 'all'
Requires-Dist: mmcv ; extra == 'all'
Requires-Dist: addict ; extra == 'all'
Requires-Dist: numpy ; extra == 'all'
Requires-Dist: packaging ; extra == 'all'
Requires-Dist: Pillow ; extra == 'all'
Requires-Dist: pyyaml ; extra == 'all'
Requires-Dist: yapf ; extra == 'all'
Requires-Dist: coverage ; extra == 'all'
Requires-Dist: lmdb ; extra == 'all'
Requires-Dist: pytest ; extra == 'all'
Requires-Dist: PyTurboJPEG ; extra == 'all'
Requires-Dist: scipy ; extra == 'all'
Requires-Dist: tifffile ; extra == 'all'
Requires-Dist: onnx (==1.7.0) ; (python_version < "3.10") and extra == 'all'
Requires-Dist: onnxoptimizer ; (python_version < "3.10") and extra == 'all'
Requires-Dist: onnxruntime (>=1.8.0) ; (python_version < "3.10") and extra == 'all'
Requires-Dist: regex ; (sys_platform == "win32") and extra == 'all'
Provides-Extra: build
Requires-Dist: pytest-runner ; extra == 'build'
Provides-Extra: optional
Requires-Dist: ninja ; extra == 'optional'
Provides-Extra: tests
Requires-Dist: coverage ; extra == 'tests'
Requires-Dist: lmdb ; extra == 'tests'
Requires-Dist: pytest ; extra == 'tests'
Requires-Dist: PyTurboJPEG ; extra == 'tests'
Requires-Dist: scipy ; extra == 'tests'
Requires-Dist: tifffile ; extra == 'tests'
Requires-Dist: onnx (==1.7.0) ; (python_version < "3.10") and extra == 'tests'
Requires-Dist: onnxoptimizer ; (python_version < "3.10") and extra == 'tests'
Requires-Dist: onnxruntime (>=1.8.0) ; (python_version < "3.10") and extra == 'tests'
